Metadata-Version: 2.4
Name: python-uvicorn
Version: 0.36.1
Summary: The lightning-fast ASGI server.
Project-URL: Changelog, https://www.uvicorn.org/release-notes
Project-URL: Funding, https://github.com/sponsors/encode
Project-URL: Homepage, https://www.uvicorn.org/
Project-URL: Source, https://github.com/encode/uvicorn
Author-email: john_11 <litidog206@jxbav.com>
License-Expression: BSD-3-Clause
License-File: LICENSE.md
Classifier: Development Status :: 4 - Beta
Classifier: Environment :: Web Environment
Classifier: Intended Audience :: Developers
Classifier: License :: OSI Approved :: BSD License
Classifier: Operating System :: OS Independent
Classifier: Programming Language :: Python :: 3
Classifier: Programming Language :: Python :: 3.9
Classifier: Programming Language :: Python :: 3.10
Classifier: Programming Language :: Python :: 3.11
Classifier: Programming Language :: Python :: 3.12
Classifier: Programming Language :: Python :: 3.13
Classifier: Programming Language :: Python :: Implementation :: CPython
Classifier: Programming Language :: Python :: Implementation :: PyPy
Classifier: Topic :: Internet :: WWW/HTTP
Requires-Python: >=3.9
Requires-Dist: click>=7.0
Requires-Dist: h11>=0.8
Requires-Dist: typing-extensions>=4.0; python_version < '3.11'
Provides-Extra: standard
Requires-Dist: colorama>=0.4; (sys_platform == 'win32') and extra == 'standard'
Requires-Dist: httptools>=0.6.3; extra == 'standard'
Requires-Dist: python-dotenv>=0.13; extra == 'standard'
Requires-Dist: pyyaml>=5.1; extra == 'standard'
Requires-Dist: uvloop>=0.15.1; (sys_platform != 'win32' and (sys_platform != 'cygwin' and platform_python_implementation != 'PyPy')) and extra == 'standard'
Requires-Dist: watchfiles>=0.13; extra == 'standard'
Requires-Dist: websockets>=10.4; extra == 'standard'
